Workbook

Sheet Working Balance
A1: Name of Case EX. Conservatorship of The Person and Estate of James H. Grizzle, Conversatee
A2: Court and Case No. EX. San Bernardino County Superior Court Case No. CONVA2400321
B4: First Account Current
B5: of Conservator, Wendy Smith, CLPF
B6: Summary of Account
B7: 9/26/24 - 11/30/25
B9: CHARGES
C10: POH Begin (Schedule B)
C11: Cash Assets | D11: ='POH @ Beginning Schedule B'!E20 -> 0
C12: Non-Cash Assets | D12: ='POH @ Beginning Schedule B'!E21 -> 0
D13: =D11+D12 -> 0
C15: Cash Receipts (Schedule A) | D15: ='Schedule A '!D46 -> 0
C16: After Acquried Assets (Schedule F) | D16: ='Schedule F'!F12 -> 0
C18: TOTAL CHARGES | D18: =SUM(D13:D16) -> 0
B20: CREDITS | M20: )
C21: POH End (Schedule E)
C22: Cash Assets | D22: ='POH @ End Schedule E'!E21 -> 0
C23: Non-Cash Assets | D23: ='POH @ End Schedule E'!E22 -> 0
D24: =D22+D23 -> 0
C26: Cash Disbursement (Schedule C) | D26: ='Schedule C'!F98 -> 0
C28: TOTAL CREDITS | D28: =SUM(D24:D27) -> 0

Sheet Statements
B2: Bank Name | I2: Bank Name | P2: Bank Name
B3: Included on I&A? | I3: Included on I&A? | P3: Included on I&A?
B4: Acct. # | C4: Date | D4: Need? | E4: Have Stmt? (1 or 0) | F4: Have Copy Chks? (1 or 0) | G4: Input ? | I4: Acct. # | J4: Date | K4: Need? | L4: Have Stmt? (1 or 0) | M4: Have Copy Chks? (1 or 0) | N4: Input ? | P4: Acct. # | Q4: Date | R4: Need? | S4: Have Stmt? (1 or 0) | T4: Have Copy Chks? (1 or 0) | U4: Input ?
B5: 9259 | C5: 45954 | I5: 9259 | J5: 45954 | P5: 9259 | Q5: 45954
C6: 45985 | J6: 45985 | Q6: 45985
C7: 46015 | J7: 46015 | Q7: 46015
C8: 45682 | J8: 45682 | Q8: 45682
C9: 45713 | J9: 45713 | Q9: 45713
C10: 45741 | J10: 45741 | Q10: 45741
C11: 45772 | J11: 45772 | Q11: 45772
C12: 45802 | J12: 45802 | Q12: 45802
C13: 45833 | J13: 45833 | Q13: 45833
C14: 45863 | J14: 45863 | Q14: 45863
C15: 45894 | J15: 45894 | Q15: 45894
C16: 45925 | J16: 45925 | Q16: 45925
C17: 45955 | J17: 45955 | Q17: 45955
C18: 45986 | J18: 45986 | Q18: 45986

Sheet Bank Statement Transactions
B2: Bank Name
B3: Date | C3: Description | D3: Acct Number | E3: Check Number | F3: Copy of Chk | G3: Debit | H3: Credit | I3: Additonal Info.
C12: TOTALS | G12: =SUM(G4:G10) -> 0 | H12: =SUM(H4:H10) -> 0
C16: BALACE AT DOD | D16: 0 | E16: TOTAL DEBT- TOTAL CREDIT | F16: =(H12-G12) -> 0 | H16: BALANCED= YES
B18: Bank Name
B19: Date | C19: Description | D19: Acct Number | E19: Check Number | F19: Copy of Chk | G19: Debit | H19: Credit | I19: Additonal Info.
C28: TOTALS | G28: =SUM(G20:G26) -> 0 | H28: =SUM(H20:H26) -> 0
C32: BALACE AT DOD | D32: 0 | E32: TOTAL DEBT- TOTAL CREDIT | F32: =(H28-G28) -> 0 | H32: BALANCED= YES

Sheet POH @ Beginning Schedule B
A2: In the Matter of
A3: Property on Hand at Beginning of Accounting Period
A4: Schedule B
A5: Valued as of Date
B7: Cash and Cash Equivalents
B8: Description | D8: Market Value | E8: Carry Value
B9: Use I&A Description
B12: Total Cash and Cash Equivalents | D12: =SUM(D9:D10) -> 0 | E12: =SUM(E9:E10) -> 0
B14: Non-Cash Assets
B15: Description | D15: Market Value | E15: Carry Value
B16: Use I&A Description
B18: Total Non-Cash Assets | D18: =SUM(D16:D16) -> 0 | E18: =SUM(E16:E16) -> 0
B20: Total Cash Assets | D20: =SUM(D12) -> 0 | E20: =SUM(E12) -> 0
B21: Total Non-Cash Assets | D21: =D18 -> 0 | E21: =E18 -> 0
B23: Total Property on Hand at the Beginning of the Accounting Period | D23: =SUM(D20:D21) -> 0 | E23: =SUM(E20:E21) -> 0

Sheet POH @ End Schedule E
A2: In the Matter of
A3: Property on Hand at End of Accounting Period
A4: Schedule E
A5: Valued as of Date
B7: Cash and Cash Equivalents
B9: Description | D9: Market Value | E9: Carry Value
B10: Use I&A Description
B12: Total Cash and Cash Equivalents | D12: =SUM(D10:D11) -> 0 | E12: =SUM(E10:E11) -> 0
B14: Non-Cash Assets
B16: Description | D16: Market Value | E16: Carry Value
B17: Use I&A Description
B19: Total Non-Cash Assets | D19: =SUM(D17:D17) -> 0 | E19: =SUM(E17:E17) -> 0
B21: Total Cash Assets | D21: =SUM(D12) -> 0 | E21: =SUM(,E12) -> 0
B22: Total Non-Cash Assets | D22: =D19 -> 0 | E22: =E19 -> 0
B24: Total Property on Hand at the End of the Accounting Period | D24: =SUM(D21:D22) -> 0 | E24: =SUM(E21:E22) -> 0

Sheet Schedule A 
A1: In the Matter of
A2: Schedule A
A3: Receipts
A4: From Date
B5: Interest:
B7: Insert name of Vendor
B8: Date | C8: Description | E8: Amount
B14: Schedule A (Continued)
C15: Total Interest | E15: =SUM(E12) -> 0
B17: Pensions, Annuities, and Other Regular Periodic Payments:
B19: Insert name of Vendor
B20: Date | C20: Description | E20: Amount
B32: Total Pensions, Annuities, and Other Regular Periodic Payments: | E32: =SUM(E29) -> 0
B34: Miscellaneous Receipts:
B36: Insert name of Vendor
B37: Date | C37: Description | E37: Amount
E42: =SUM(E38:E40) -> 0
C44: Total Miscellaneous Receipts | E44: =SUM(E42) -> 0
C46: Total Schedule A | D46: =SUM(E44,E32,E15) -> 0

Sheet Schedule C
B1: In the Matter of
B2: Schedule C
B3: Disbursements
B4: From Date
B5: Residential Facility/Caregiver:
B8: Insert name of Vendor
B9: Date | C9: Account | D9: Description | E9: Check | F9: Amount
F21: =SUM(F10:F19) -> 0
C23: Total Residential Facility/Caregiver: | F23: =SUM(F21) -> 0
B25: Living Expenses:
B27: Insert name of Vendor
B28: Date | C28: Account | D28: Description | E28: Check | F28: Amount
D43: Total Living Expenses | F43: =SUM(F40) -> 0
B45: Medical Expenses
B47: Insert name of Vendor
B48: Date | C48: Account | D48: Description | E48: Check | F48: Amount
F56: =SUM(F49:F55) -> 0
C59: Total Medical Expenses | F59: =SUM(F56) -> 0
B62: Legal & Related Professional Expenses:
B64: Insert name of Vendor
B65: Date | C65: Account | D65: Description | E65: Check | F65: Amount
C72: Total Legal & Related Professional Expenses | F72: =SUM(F70) -> 0
B75: Insurance
B77: Insert name of Vendor
B78: Date | C78: Account | D78: Description | E78: Check | F78: Amount
D84: Total Transamerica Life Insurance | F84: =SUM(F79:F95) -> 0
D86: Total Insurance Expenses | F86: =SUM(F84) -> 0
B88: Miscellanous
B90: Insert name of Vendor
B91: Date | C91: Account | D91: Description | E91: Check | F91: Amount
D98: Total Schedule C | F98: =SUM(F86,F72,F59,F43,F23) -> 0

Sheet Schedule F
B2: In the Matter of
B3: Schedule F
B4: Additional Property Received During the Accounting Period
B5: From
B6: Date | C6: Description | F6: Carry Value
D10: Total Additional Property Received | F10: =SUM(F7:F9) -> 0
D12: Total Schedule F | F12: =F10 -> 0
